rialto/__init__.py
rialto/common/__init__.py
rialto/common/env_yaml.py
rialto/common/table_reader.py
rialto/common/utils.py
rialto/jobs/__init__.py
rialto/jobs/decorators.py
rialto/jobs/job_base.py
rialto/jobs/module_register.py
rialto/jobs/resolver.py
rialto/jobs/test_utils.py
rialto/loader/__init__.py
rialto/loader/config_loader.py
rialto/loader/interfaces.py
rialto/loader/pyspark_feature_loader.py
rialto/maker/__init__.py
rialto/maker/containers.py
rialto/maker/feature_maker.py
rialto/maker/utils.py
rialto/maker/wrappers.py
rialto/metadata/__init__.py
rialto/metadata/data_classes/__init__.py
rialto/metadata/data_classes/feature_metadata.py
rialto/metadata/data_classes/group_metadata.py
rialto/metadata/enums.py
rialto/metadata/metadata_manager.py
rialto/metadata/utils.py
rialto/runner/__init__.py
rialto/runner/config_loader.py
rialto/runner/config_overrides.py
rialto/runner/date_manager.py
rialto/runner/reporting/__init__.py
rialto/runner/reporting/bookkeeper.py
rialto/runner/reporting/mailer.py
rialto/runner/reporting/record.py
rialto/runner/reporting/tracker.py
rialto/runner/runner.py
rialto/runner/table.py
rialto/runner/transformation.py
rialto/runner/utils.py
rialto-2.0.11.dist-info/LICENSE
rialto-2.0.11.dist-info/METADATA
rialto-2.0.11.dist-info/WHEEL
rialto-2.0.11.dist-info/RECORD
